Visuals/FastMatplot.py
Visuals/LaTex.py
Visuals/__init__.py
Visuals/_base_/__init__.py
Visuals/_base_/_axes_base.py
Visuals/_base_/_graph_base.py
Visuals/_utils_/__init__.py
Visuals/_utils_/_exceptions.py
Visuals/_utils_/_functions.py
Visuals/_utils_/_type_definitions.py
jp_notebook_utils-1.0.1.2.dist-info/LICENSE
jp_notebook_utils-1.0.1.2.dist-info/METADATA
jp_notebook_utils-1.0.1.2.dist-info/WHEEL
jp_notebook_utils-1.0.1.2.dist-info/top_level.txt
jp_notebook_utils-1.0.1.2.dist-info/RECORD
